{"type": "FeatureCollection", "features": [{"type": "Feature", "geometry": {"type": "Point", "coordinates": [103.85092207834701, 1.355282626697445]}, "properties": {"OBJECTID": 332, "VENUE": "Bishan Sport Centre", "ADDRESSBLOCKHOUSENUMBER": "5", "ADDRESSSTREETNAME": "Bishan Street 14", "POSTAL_CODE": "579783", "DETAILS": "https://www.activesgcircle.gov.sg/facilities", "INC_CRC": "8BBE9814CB5F5705", "FMEL_UPD_D": "20241024152749"}}, {"type": "Feature", "geometry": {"type": "Point", "coordinates": [103.84999045199592, 1.355075019303503]}, "properties": {"OBJECTID": 333, "VENUE": "Bishan Clubhouse", "ADDRESSBLOCKHOUSENUMBER": "3", "ADDRESSSTREETNAME": "Bishan Street 14", "POSTAL_CODE": "579780", "DETAILS": "https://www.activesgcircle.gov.sg/facilities", "INC_CRC": "68CF1CA26E294D0B", "FMEL_UPD_D": "20241024152749"}}]}