{"type": "FeatureCollection", "features": [{"type": "Feature", "geometry": {"type": "Point", "coordinates": [103.84761124346433, 1.3043760852669966]}, "properties": {"OBJECTID": 67592, "NAME": "MOUNT EMILY PK", "X": 29590.64261636, "Y": 31856.80304999, "INC_CRC": "7D0F0F0743A8873B", "FMEL_UPD_D": "20260115000356"}}]}