{"type": "FeatureCollection", "features": [{"type": "Feature", "properties": {"Name": "kml_127", "Description": "<center><table><tr><th colspan='2' align='center'><em>Attributes</em></th></tr><tr bgcolor=\"#E3E3F3\"> <th>HCI_CODE</th> <td>9403966</td> </tr><tr bgcolor=\"\"> <th>HCI_NAME</th> <td>CHESTMED pte ltd</td> </tr><tr bgcolor=\"#E3E3F3\"> <th>LICENCE_TYPE</th> <td>MC</td> </tr><tr bgcolor=\"\"> <th>HCI_TEL</th> <td>62351466</td> </tr><tr bgcolor=\"#E3E3F3\"> <th>POSTAL_CD</th> <td>228510</td> </tr><tr bgcolor=\"\"> <th>ADDR_TYPE</th> <td>B</td> </tr><tr bgcolor=\"#E3E3F3\"> <th>BLK_HSE_NO</th> <td>3</td> </tr><tr bgcolor=\"\"> <th>FLOOR_NO</th> <td>12</td> </tr><tr bgcolor=\"#E3E3F3\"> <th>UNIT_NO</th> <td>03</td> </tr><tr bgcolor=\"\"> <th>STREET_NAME</th> <td>Mount Elizabeth</td> </tr><tr bgcolor=\"#E3E3F3\"> <th>BUILDING_NAME</th> <td>Mount Elizabeth Medical Centre</td> </tr><tr bgcolor=\"\"> <th>CLINIC_PROGRAMME_CODE</th> <td>CDMP,CHAS,ISP</td> </tr><tr bgcolor=\"#E3E3F3\"> <th>X_COORDINATE</th> <td>28236.02090344</td> </tr><tr bgcolor=\"\"> <th>Y_COORDINATE</th> <td>31944.05636556</td> </tr><tr bgcolor=\"#E3E3F3\"> <th>INC_CRC</th> <td>C8D429103E779FE6</td> </tr><tr bgcolor=\"\"> <th>FMEL_UPD_D</th> <td>20210926121846</td> </tr></table></center>"}, "geometry": {"type": "Point", "coordinates": [103.83543933754, 1.30516521414744, 0.0]}}, {"type": "Feature", "properties": {"Name": "kml_1041", "Description": "<center><table><tr><th colspan='2' align='center'><em>Attributes</em></th></tr><tr bgcolor=\"#E3E3F3\"> <th>HCI_CODE</th> <td>9404706</td> </tr><tr bgcolor=\"\"> <th>HCI_NAME</th> <td>The Singapore Clinic for Kidney Diseases (Pte Ltd)</td> </tr><tr bgcolor=\"#E3E3F3\"> <th>LICENCE_TYPE</th> <td>MC</td> </tr><tr bgcolor=\"\"> <th>HCI_TEL</th> <td>67353513</td> </tr><tr bgcolor=\"#E3E3F3\"> <th>POSTAL_CD</th> <td>228510</td> </tr><tr bgcolor=\"\"> <th>ADDR_TYPE</th> <td>B</td> </tr><tr bgcolor=\"#E3E3F3\"> <th>BLK_HSE_NO</th> <td>3</td> </tr><tr bgcolor=\"\"> <th>FLOOR_NO</th> <td>08</td> </tr><tr bgcolor=\"#E3E3F3\"> <th>UNIT_NO</th> <td>01</td> </tr><tr bgcolor=\"\"> <th>STREET_NAME</th> <td>MOUNT ELIZABETH</td> </tr><tr bgcolor=\"#E3E3F3\"> <th>BUILDING_NAME</th> <td>MOUNT ELIZABETH MEDICAL CENTRE</td> </tr><tr bgcolor=\"\"> <th>CLINIC_PROGRAMME_CODE</th> <td>CDMP,CHAS</td> </tr><tr bgcolor=\"#E3E3F3\"> <th>X_COORDINATE</th> <td>28236.02090344</td> </tr><tr bgcolor=\"\"> <th>Y_COORDINATE</th> <td>31944.05636556</td> </tr><tr bgcolor=\"#E3E3F3\"> <th>INC_CRC</th> <td>C8D429105EF2776B</td> </tr><tr bgcolor=\"\"> <th>FMEL_UPD_D</th> <td>20210926121846</td> </tr></table></center>"}, "geometry": {"type": "Point", "coordinates": [103.83543933754, 1.30516521414744, 0.0]}}, {"type": "Feature", "properties": {"Name": "kml_1121", "Description": "<center><table><tr><th colspan='2' align='center'><em>Attributes</em></th></tr><tr bgcolor=\"#E3E3F3\"> <th>HCI_CODE</th> <td>9403436</td> </tr><tr bgcolor=\"\"> <th>HCI_NAME</th> <td>THE BALMORAL CLINIC  FAMILY MEDICINE</td> </tr><tr bgcolor=\"#E3E3F3\"> <th>LICENCE_TYPE</th> <td>MC</td> </tr><tr bgcolor=\"\"> <th>HCI_TEL</th> <td>67322033</td> </tr><tr bgcolor=\"#E3E3F3\"> <th>POSTAL_CD</th> <td>259708</td> </tr><tr bgcolor=\"\"> <th>ADDR_TYPE</th> <td>B</td> </tr><tr bgcolor=\"#E3E3F3\"> <th>BLK_HSE_NO</th> <td>271</td> </tr><tr bgcolor=\"\"> <th>FLOOR_NO</th> <td>02</td> </tr><tr bgcolor=\"#E3E3F3\"> <th>UNIT_NO</th> <td>12</td> </tr><tr bgcolor=\"\"> <th>STREET_NAME</th> <td>BUKIT TIMAH RD</td> </tr><tr bgcolor=\"#E3E3F3\"> <th>BUILDING_NAME</th> <td>BALMORAL PLAZA</td> </tr><tr bgcolor=\"\"> <th>CLINIC_PROGRAMME_CODE</th> <td>CDMP,CHAS</td> </tr><tr bgcolor=\"#E3E3F3\"> <th>X_COORDINATE</th> <td>28241.3892633</td> </tr><tr bgcolor=\"\"> <th>Y_COORDINATE</th> <td>33190.72333378</td> </tr><tr bgcolor=\"#E3E3F3\"> <th>INC_CRC</th> <td>BF36398292EAB639</td> </tr><tr bgcolor=\"\"> <th>FMEL_UPD_D</th> <td>20210926121846</td> </tr></table></center>"}, "geometry": {"type": "Point", "coordinates": [103.835487584763, 1.31643962977729, 0.0]}}]}