{"type": "FeatureCollection", "features": [{"type": "Feature", "properties": {"Name": "kml_159", "Description": "<center><table><tr><th colspan='2' align='center'><em>Attributes</em></th></tr><tr bgcolor=\"#E3E3F3\"> <th>CENTRE_NAME</th> <td>HOUSE ON THE HILL PTE. LTD.</td> </tr><tr bgcolor=\"\"> <th>CENTRE_CODE</th> <td>PT9477</td> </tr><tr bgcolor=\"#E3E3F3\"> <th>INC_CRC</th> <td>716FA5A51AA32F89</td> </tr><tr bgcolor=\"\"> <th>FMEL_UPD_D</th> <td>20211201093631</td> </tr></table></center>"}, "geometry": {"type": "Point", "coordinates": [103.833985815703, 1.3151352310717, 0.0]}}, {"type": "Feature", "properties": {"Name": "kml_184", "Description": "<center><table><tr><th colspan='2' align='center'><em>Attributes</em></th></tr><tr bgcolor=\"#E3E3F3\"> <th>CENTRE_NAME</th> <td>CAMBERLEY INTERNATIONAL PRE-SCHOOL PRIVATE LIMITED</td> </tr><tr bgcolor=\"\"> <th>CENTRE_CODE</th> <td>PT9206</td> </tr><tr bgcolor=\"#E3E3F3\"> <th>INC_CRC</th> <td>3BFE8F8C3D8929E9</td> </tr><tr bgcolor=\"\"> <th>FMEL_UPD_D</th> <td>20211201093631</td> </tr></table></center>"}, "geometry": {"type": "Point", "coordinates": [103.835487591952, 1.31643962615982, 0.0]}}, {"type": "Feature", "properties": {"Name": "kml_463", "Description": "<center><table><tr><th colspan='2' align='center'><em>Attributes</em></th></tr><tr bgcolor=\"#E3E3F3\"> <th>CENTRE_NAME</th> <td>KIDDIWINKIE SCHOOLHOUSE PTE. LTD.</td> </tr><tr bgcolor=\"\"> <th>CENTRE_CODE</th> <td>PT5280</td> </tr><tr bgcolor=\"#E3E3F3\"> <th>INC_CRC</th> <td>A3EEF87051A02230</td> </tr><tr bgcolor=\"\"> <th>FMEL_UPD_D</th> <td>20211201093631</td> </tr></table></center>"}, "geometry": {"type": "Point", "coordinates": [103.839900765588, 1.31039580336593, 0.0]}}, {"type": "Feature", "properties": {"Name": "kml_716", "Description": "<center><table><tr><th colspan='2' align='center'><em>Attributes</em></th></tr><tr bgcolor=\"#E3E3F3\"> <th>CENTRE_NAME</th> <td>MULBERRY LEARNING CENTRE CENTRAL PTE LTD</td> </tr><tr bgcolor=\"\"> <th>CENTRE_CODE</th> <td>PT9267</td> </tr><tr bgcolor=\"#E3E3F3\"> <th>INC_CRC</th> <td>99CE8EE20BD3D1D5</td> </tr><tr bgcolor=\"\"> <th>FMEL_UPD_D</th> <td>20211201093631</td> </tr></table></center>"}, "geometry": {"type": "Point", "coordinates": [103.838864880096, 1.3104343381511, 0.0]}}, {"type": "Feature", "properties": {"Name": "kml_999", "Description": "<center><table><tr><th colspan='2' align='center'><em>Attributes</em></th></tr><tr bgcolor=\"#E3E3F3\"> <th>CENTRE_NAME</th> <td>PAT'S SCHOOLHOUSE PTE LTD</td> </tr><tr bgcolor=\"\"> <th>CENTRE_CODE</th> <td>PT0890</td> </tr><tr bgcolor=\"#E3E3F3\"> <th>INC_CRC</th> <td>4E5BB839B12A80EB</td> </tr><tr bgcolor=\"\"> <th>FMEL_UPD_D</th> <td>20211201093631</td> </tr></table></center>"}, "geometry": {"type": "Point", "coordinates": [103.829785239581, 1.30839392038818, 0.0]}}, {"type": "Feature", "properties": {"Name": "kml_1002", "Description": "<center><table><tr><th colspan='2' align='center'><em>Attributes</em></th></tr><tr bgcolor=\"#E3E3F3\"> <th>CENTRE_NAME</th> <td>PAT'S SCHOOLHOUSE PTE LTD</td> </tr><tr bgcolor=\"\"> <th>CENTRE_CODE</th> <td>PT8374</td> </tr><tr bgcolor=\"#E3E3F3\"> <th>INC_CRC</th> <td>F67018CFC5B56644</td> </tr><tr bgcolor=\"\"> <th>FMEL_UPD_D</th> <td>20211201093631</td> </tr></table></center>"}, "geometry": {"type": "Point", "coordinates": [103.847965265346, 1.30389868987308, 0.0]}}, {"type": "Feature", "properties": {"Name": "kml_1567", "Description": "<center><table><tr><th colspan='2' align='center'><em>Attributes</em></th></tr><tr bgcolor=\"#E3E3F3\"> <th>CENTRE_NAME</th> <td>ZEE PLAYHOUSE PTE LTD</td> </tr><tr bgcolor=\"\"> <th>CENTRE_CODE</th> <td>PT8868</td> </tr><tr bgcolor=\"#E3E3F3\"> <th>INC_CRC</th> <td>7E97ABAD8F6FBC92</td> </tr><tr bgcolor=\"\"> <th>FMEL_UPD_D</th> <td>20211201093632</td> </tr></table></center>"}, "geometry": {"type": "Point", "coordinates": [103.836319587412, 1.31514831823003, 0.0]}}]}